vsvn_rag/__init__.py
vsvn_rag/chunker/__init__.py
vsvn_rag/chunker/base_chunker.py
vsvn_rag/chunker/doc_chunker.py
vsvn_rag/chunker/pdf_chunker.py
vsvn_rag/chunker/ppt_chunker.py
vsvn_rag/chunker/rule_chunker.py
vsvn_rag/chunker/xls_chunker.py
vsvn_rag/config/__init__.py
vsvn_rag/docs/__init__.py
vsvn_rag/embedder/__init__.py
vsvn_rag/embedder/base_embedder.py
vsvn_rag/embedder/demo_embedding.py
vsvn_rag/embedder/offline_embedder.py
vsvn_rag/embedder/openai_embedder.py
vsvn_rag/generator/__init__.py
vsvn_rag/generator/base_generator.py
vsvn_rag/generator/formatter.py
vsvn_rag/generator/openai_generator.py
vsvn_rag/generator/prompt_template.py
vsvn_rag/pipeline/__init__.py
vsvn_rag/pipeline/runner.py
vsvn_rag/reader/__init__.py
vsvn_rag/reader/base_loader.py
vsvn_rag/reader/doc_loader.py
vsvn_rag/reader/pdf_loader.py
vsvn_rag/reader/ppt_loader.py
vsvn_rag/reader/sharepoint_loader.py
vsvn_rag/reader/xls_loader.py
vsvn_rag/retriever/__init__.py
vsvn_rag/retriever/base_retriever.py
vsvn_rag/retriever/bm25.py
vsvn_rag/retriever/hybrid.py
vsvn_rag/retriever/reranker.py
vsvn_rag/shared/__init__.py
vsvn_rag/shared/schema.py
vsvn_rag/utils/__init__.py
vsvn_rag/utils/cost_tracker.py
vsvn_rag/utils/eval_metrics.py
vsvn_rag/utils/logger.py
vsvn_rag/vectorstore/__init__.py
vsvn_rag/vectorstore/base_vector_store.py
vsvn_rag/vectorstore/connect_qdrant.py
vsvn_rag/vectorstore/qdrant_store.py
vsvn_rag-0.1.0.dist-info/METADATA
vsvn_rag-0.1.0.dist-info/WHEEL
vsvn_rag-0.1.0.dist-info/top_level.txt
vsvn_rag-0.1.0.dist-info/RECORD
