Metadata-Version: 2.4
Name: vsvn_rag
Version: 0.1.0
Summary: Modular Retrieval-Augmented Generation System
Author: VSVN_AI TEAM
Classifier: Programming Language :: Python :: 3
Classifier: Operating System :: OS Independent
Requires-Python: >=3.8
Requires-Dist: PyYAML
Requires-Dist: PyPDF2
Requires-Dist: numpy
Requires-Dist: scikit-learn
Dynamic: author
Dynamic: classifier
Dynamic: description
Dynamic: description-content-type
Dynamic: requires-dist
Dynamic: requires-python
Dynamic: summary
